LICENSE.txt
setup.cfg
setup.py
moduletest1/__init__.py
moduletest1/te.py
moduletest12.egg-info/PKG-INFO
moduletest12.egg-info/SOURCES.txt
moduletest12.egg-info/dependency_links.txt
moduletest12.egg-info/not-zip-safe
moduletest12.egg-info/requires.txt
moduletest12.egg-info/top_level.txt