Metadata-Version: 2.1
Name: moduletest12
Version: 1.4
Summary: A mini spider framework, like Scrapy
Author: davezj127
Author-email: davezj127@gmail.com
License: Apache License v2
Classifier: Programming Language :: Python
Classifier: Operating System :: Microsoft :: Windows
Classifier: Operating System :: Unix
Requires-Python: >=3.6
License-File: LICENSE.txt
Requires-Dist: requests>=2.18.4
Requires-Dist: six>=1.11.0
